superduper_torch/__init__.py
superduper_torch/encoder.py
superduper_torch/model.py
superduper_torch/training.py
superduper_torch/utils.py
superduper_torch-0.10.0.dist-info/licenses/LICENSE
superduper_torch-0.10.0.dist-info/METADATA
superduper_torch-0.10.0.dist-info/WHEEL
superduper_torch-0.10.0.dist-info/top_level.txt
superduper_torch-0.10.0.dist-info/RECORD
