Metadata-Version: 2.4
Name: superduper_torch
Version: 0.10.0
Summary: Superduper allows users to work with arbitrary `torch` models, with custom pre-, post-processing and input/ output data-types, as well as offering training with superduper
Maintainer-email: "superduper.io, Inc." <opensource@superduper.io>
License: 
Project-URL: homepage, https://superduper.io
Project-URL: documentation, https://docs.superduper.io/docs/intro
Project-URL: source, https://github.com/superduper-io/superduper
Keywords: databases,mongodb,data-science,machine-learning,mlops,vector-database,ai
Requires-Python: >=3.10
License-File: LICENSE
Requires-Dist: torch>=2.1.2
Requires-Dist: torchvision>=0.17.1
Provides-Extra: test
Dynamic: license-file
